Metadata-Version: 2.1
Name: Topsis-Twinkle-101903209
Version: 0.0.1
Summary: A Python package to find TOPSIS for multi-criteria decision analysis method
Home-page: UNKNOWN
Author: Twinkle Garg
Author-email: ttwinkle_be19@thapar.edu
License: MIT
Keywords: topsis,UCS654,TIET
Platform: UNKNOWN
Classifier: Development Status :: 3 - Alpha
Classifier: Intended Audience :: Developers
Classifier: Operating System :: Microsoft :: Windows :: Windows 10
Classifier: License :: OSI Approved :: MIT License
Classifier: Programming Language :: Python :: 3
License-File: LICENSE.txt
